SimpleStepperLoggerDriverV1/SimpleStepperLoggerDriverV1.py
SimpleStepperLoggerDriverV1/__init__.py
SimpleStepperLoggerDriverV1/main.py
simplestepperloggerdriverv1-0.1.0.dist-info/METADATA
simplestepperloggerdriverv1-0.1.0.dist-info/WHEEL
simplestepperloggerdriverv1-0.1.0.dist-info/licenses/LICENSE
simplestepperloggerdriverv1-0.1.0.dist-info/RECORD
