Metadata-Version: 2.3
Name: SimpleStepperLoggerDriverV1
Version: 0.1.0
Summary: Small library to communicate with SimpleStepperLoggerDriverV1
Author-email: Aleksei Karavaev <alexok997@gmail.com>
Classifier: License :: OSI Approved :: MIT License
Classifier: Operating System :: OS Independent
Classifier: Programming Language :: Python :: 3
Requires-Python: >=3.10
Requires-Dist: numpy
Requires-Dist: pymodbus>=3.5
Requires-Dist: pyserial
